powerful_benchmarker/__init__.py
powerful_benchmarker/aggregators/__init__.py
powerful_benchmarker/aggregators/base_aggregator.py
powerful_benchmarker/aggregators/mean_aggregator.py
powerful_benchmarker/api_parsers/__init__.py
powerful_benchmarker/api_parsers/api_cascaded_embeddings.py
powerful_benchmarker/api_parsers/api_deep_adversarial_metric_learning.py
powerful_benchmarker/api_parsers/api_train_with_classifier.py
powerful_benchmarker/api_parsers/api_unsupervised_embeddings_using_augmentations.py
powerful_benchmarker/api_parsers/base_api_parser.py
powerful_benchmarker/api_parsers/folder_creator.py
powerful_benchmarker/api_parsers/getter_and_setter.py
powerful_benchmarker/architectures/__init__.py
powerful_benchmarker/architectures/misc_models.py
powerful_benchmarker/configs/__init__.py
powerful_benchmarker/configs/config_foldernames.yaml
powerful_benchmarker/configs/config_dataset/default.yaml
powerful_benchmarker/configs/config_dataset/with_cars196.yaml
powerful_benchmarker/configs/config_dataset/with_sop.yaml
powerful_benchmarker/configs/config_eval/default.yaml
powerful_benchmarker/configs/config_eval/with_32_workers.yaml
powerful_benchmarker/configs/config_factories/default.yaml
powerful_benchmarker/configs/config_general/default.yaml
powerful_benchmarker/configs/config_general/with_256_batch.yaml
powerful_benchmarker/configs/config_general/with_32_workers.yaml
powerful_benchmarker/configs/config_general/with_cars196.yaml
powerful_benchmarker/configs/config_general/with_cascaded.yaml
powerful_benchmarker/configs/config_general/with_classifier.yaml
powerful_benchmarker/configs/config_general/with_daml.yaml
powerful_benchmarker/configs/config_general/with_sop.yaml
powerful_benchmarker/configs/config_general/with_unsupervised.yaml
powerful_benchmarker/configs/config_loss_and_miners/default.yaml
powerful_benchmarker/configs/config_loss_and_miners/with_cascaded.yaml
powerful_benchmarker/configs/config_loss_and_miners/with_classification_based_loss.yaml
powerful_benchmarker-0.9.33.dist-info/METADATA
powerful_benchmarker-0.9.33.dist-info/WHEEL
powerful_benchmarker-0.9.33.dist-info/top_level.txt
powerful_benchmarker-0.9.33.dist-info/RECORD
