Metadata-Version: 2.1
Name: powerful-benchmarker
Version: 0.9.33
Summary: A PyTorch library for benchmarking deep metric learning. It's powerful.
Home-page: https://github.com/KevinMusgrave/powerful-benchmarker
Author: Kevin Musgrave
Author-email: tkm45@cornell.edu
License: UNKNOWN
Platform: UNKNOWN
Classifier: Programming Language :: Python :: 3
Classifier: License :: OSI Approved :: MIT License
Classifier: Operating System :: OS Independent
Requires-Python: >=3.0
Requires-Dist: numpy
Requires-Dist: scikit-learn
Requires-Dist: torch
Requires-Dist: torchvision
Requires-Dist: easy-module-attribute-getter (==0.9.41)
Requires-Dist: record-keeper (==0.9.29)
Requires-Dist: tensorboard
Requires-Dist: matplotlib
Requires-Dist: pretrainedmodels
Requires-Dist: pytorch-metric-learning (==0.9.92)
Requires-Dist: pandas
Requires-Dist: ax-platform
Requires-Dist: faiss-gpu
Requires-Dist: gdown (>=3.12.0)
